README.md
setup.py
distributions_altered/Binomialdistribution.py
distributions_altered/Gaussiandistribution.py
distributions_altered/Generaldistribution.py
distributions_altered/__init__.py
distributions_altered.egg-info/PKG-INFO
distributions_altered.egg-info/SOURCES.txt
distributions_altered.egg-info/dependency_links.txt
distributions_altered.egg-info/not-zip-safe
distributions_altered.egg-info/top_level.txt